RismTemplate/__init__.py
RismTemplate/main.py
RismTemplate-0.0.2.dist-info/LICENSE
RismTemplate-0.0.2.dist-info/METADATA
RismTemplate-0.0.2.dist-info/WHEEL
RismTemplate-0.0.2.dist-info/top_level.txt
RismTemplate-0.0.2.dist-info/RECORD
