Metadata-Version: 2.1
Name: RismTemplate
Version: 0.0.2
Summary: Quickly `generate new code` with less `repetitive coding` using `predefined templates`
Author-email: Risky Mulya Nugraha <riskymulya@protonmail.com>
Project-URL: Homepage, https://github.com/rizmulya/RismTemplate.git
Project-URL: Bug Tracker, https://github.com/rizmulya/RismTemplate
Classifier: Programming Language :: Python :: 3
Classifier: License :: OSI Approved :: GNU General Public License v3 (GPLv3)
Classifier: Operating System :: OS Independent
Requires-Python: >=3.7
License-File: LICENSE
Requires-Dist: jinja2 ==3.1.3
Requires-Dist: inflect ==7.2.0
